yadl/__init__.py
yadl-0.1.0.dist-info/METADATA
yadl-0.1.0.dist-info/WHEEL
yadl-0.1.0.dist-info/top_level.txt
yadl-0.1.0.dist-info/RECORD
