Metadata-Version: 2.1
Name: yadl
Version: 0.1.0
Summary: Yet another dotenv library
Home-page: UNKNOWN
Author: Ivan Kapranov koltiradw@yandex.ru
License: MIT
Platform: UNKNOWN
